MMP_PaintGunParam/CustomModbusClient.py
MMP_PaintGunParam/Gun_OFF.py
MMP_PaintGunParam/Gun_ON.py
MMP_PaintGunParam/__init__.py
MMP_PaintGunParam/paint_gun_param_handler.py
mmp_paintgunparam-0.1.1.dist-info/METADATA
mmp_paintgunparam-0.1.1.dist-info/WHEEL
mmp_paintgunparam-0.1.1.dist-info/top_level.txt
mmp_paintgunparam-0.1.1.dist-info/RECORD
